devpi_rss/__init__.py
devpi_rss/views.py
devpi_rss/static/style.css
devpi_rss/templates/macros.pt
devpi_rss-1.0.9.dist-info/DESCRIPTION.rst
devpi_rss-1.0.9.dist-info/METADATA
devpi_rss-1.0.9.dist-info/RECORD
devpi_rss-1.0.9.dist-info/WHEEL
devpi_rss-1.0.9.dist-info/entry_points.txt
devpi_rss-1.0.9.dist-info/metadata.json
devpi_rss-1.0.9.dist-info/top_level.txt
