Metadata-Version: 2.0
Name: devpi-rss
Version: 1.0.9
Summary: A plug-in for devpi-server which generates RSS feeds for indices.
Home-page: https://github.com/k-bu/devpi-rss
Author: k-bu
Author-email: k-bu@email.com
License: MIT
Platform: UNKNOWN
Classifier: Environment :: Web Environment
Classifier: Intended Audience :: Developers
Classifier: Intended Audience :: System Administrators
Classifier: Natural Language :: English
Classifier: License :: OSI Approved :: MIT License
Classifier: Operating System :: OS Independent
Classifier: Programming Language :: Python
Classifier: Topic :: Software Development :: Libraries :: Python Modules
Requires-Dist: PyRSS2Gen
Requires-Dist: devpi-server (>=2.2.2)
Requires-Dist: devpi-web (>=2.4.0)
